kalmangrad/__init__.py
kalmangrad/grad.py
kalmangrad/version.py
kalmangrad-0.0.4.dist-info/METADATA
kalmangrad-0.0.4.dist-info/WHEEL
kalmangrad-0.0.4.dist-info/top_level.txt
kalmangrad-0.0.4.dist-info/RECORD
