Metadata-Version: 2.1
Name: kalmangrad
Version: 0.0.4
Summary: Automated, smooth, N'th order derivatives of non-uniformly sampled time series data
Home-page: https://github.com/hugohadfield/kalmangrad
Author: Hugo Hadfield
Author-email: hadfield.hugo@gmail.com
Classifier: Programming Language :: Python :: 3
Classifier: Operating System :: OS Independent
Classifier: Intended Audience :: Science/Research
Classifier: Topic :: Scientific/Engineering :: Mathematics
Classifier: License :: OSI Approved :: MIT License
Requires-Python: >=3.6
Requires-Dist: numpy
Requires-Dist: bayesfilter
